pyclibase/__init__.py
pyclibase/pyclibase.py
pyclibase-0.2.8.dist-info/LICENSE
pyclibase-0.2.8.dist-info/METADATA
pyclibase-0.2.8.dist-info/WHEEL
pyclibase-0.2.8.dist-info/top_level.txt
pyclibase-0.2.8.dist-info/RECORD
