Metadata-Version: 2.1
Name: pyclibase
Version: 0.2.8
Summary: A base class of python cli
Home-page: https://github.com/ksungkeun84/pyclibase
Author: Sungkeun Kim
Author-email: danguria@gmail.com
License: UNKNOWN
Project-URL: Bug Tracker, https://github.com/ksungkeun84/pyclibase/issues
Platform: UNKNOWN
Classifier: Programming Language :: Python :: 3
Classifier: License :: OSI Approved :: MIT License
Classifier: Operating System :: OS Independent
Requires-Python: >=3.6
License-File: LICENSE
Requires-Dist: setuptools (>=42)
Requires-Dist: wheel
Requires-Dist: rich
Requires-Dist: pyfiglet
